README.rst
setup.cfg
setup.py
dynamolock/__init__.py
dynamolock/client.py
dynamolock/context.py
dynamolock/lock.py
dynamolock/policy.py
dynamolock/schema.py
dynamolock/test_lock.py
dynamolock/worker.py
dynamolock.egg-info/PKG-INFO
dynamolock.egg-info/SOURCES.txt
dynamolock.egg-info/dependency_links.txt
dynamolock.egg-info/pbr.json
dynamolock.egg-info/requires.txt
dynamolock.egg-info/top_level.txt
dynamolock.egg-info/zip-safe